jk_mounting/MountInfo.py
jk_mounting/MountOptions.py
jk_mounting/Mounter.py
jk_mounting/__init__.py
jk_mounting-0.2025.7.12.dist-info/WHEEL
jk_mounting-0.2025.7.12.dist-info/METADATA
jk_mounting-0.2025.7.12.dist-info/RECORD
