Metadata-Version: 2.1
Name: jk_mounting
Version: 0.2025.7.12
Summary: This python module provides support for retrieving mount information and assists in mounting and unmounting.
Keywords: mount,mounting,umount,fstype
Author-email: Jürgen Knauth <pubsrc@binary-overflow.de>
Maintainer-email: Jürgen Knauth <pubsrc@binary-overflow.de>
Requires-Python: >=3.8
Classifier: Development Status :: 5 - Production/Stable
Classifier: License :: OSI Approved :: Apache Software License
Classifier: Programming Language :: Python :: 3
Requires-Dist: jk_simpleexec >= 0.2024.8.11
Requires-Dist: jk_prettyprintobj >= 0.2024.8.6
